ragflow_retrieval_mcp_server/__init__.py
ragflow_retrieval_mcp_server/server.py
ragflow_retrieval_mcp_server-0.1.1.dist-info/METADATA
ragflow_retrieval_mcp_server-0.1.1.dist-info/WHEEL
ragflow_retrieval_mcp_server-0.1.1.dist-info/entry_points.txt
ragflow_retrieval_mcp_server-0.1.1.dist-info/RECORD
