Metadata-Version: 2.4
Name: ragflow-retrieval-mcp-server
Version: 0.1.1
Summary: This mcp server is used to search content from the ragflow knowledge base.
Author-email: "data.hwc" <data.hwc@live.com>
Requires-Python: >=3.10
Requires-Dist: aiohttp>=3.11.14
Requires-Dist: mcp[cli]>=1.6.0
